{
  "/*404": [
    {
      "type": "script",
      "href": "/assets/_...404_-e86842d2.js"
    },
    {
      "type": "script",
      "href": "/assets/entry-client-503078e3.js"
    },
    {
      "type": "style",
      "href": "/assets/entry-client-2ac6917b.css"
    }
  ],
  "/cv/": [
    {
      "type": "script",
      "href": "/assets/index-9e7f63dd.js"
    },
    {
      "type": "script",
      "href": "/assets/entry-client-503078e3.js"
    },
    {
      "type": "style",
      "href": "/assets/entry-client-2ac6917b.css"
    },
    {
      "type": "script",
      "href": "/assets/Card-9aaf02af.js"
    },
    {
      "type": "style",
      "href": "/assets/Card-73b0cb51.css"
    },
    {
      "type": "style",
      "href": "/assets/index-bfe03ba4.css"
    }
  ],
  "/fun": [
    {
      "type": "script",
      "href": "/assets/fun-715d82a8.js"
    },
    {
      "type": "script",
      "href": "/assets/entry-client-503078e3.js"
    },
    {
      "type": "style",
      "href": "/assets/entry-client-2ac6917b.css"
    },
    {
      "type": "script",
      "href": "/assets/Card-9aaf02af.js"
    },
    {
      "type": "style",
      "href": "/assets/Card-73b0cb51.css"
    }
  ],
  "/": [
    {
      "type": "script",
      "href": "/assets/index-c1ca3a92.js"
    },
    {
      "type": "script",
      "href": "/assets/entry-client-503078e3.js"
    },
    {
      "type": "style",
      "href": "/assets/entry-client-2ac6917b.css"
    },
    {
      "type": "script",
      "href": "/assets/Card-9aaf02af.js"
    },
    {
      "type": "style",
      "href": "/assets/Card-73b0cb51.css"
    }
  ],
  "/research": [
    {
      "type": "script",
      "href": "/assets/research-c3e7189c.js"
    },
    {
      "type": "script",
      "href": "/assets/entry-client-503078e3.js"
    },
    {
      "type": "style",
      "href": "/assets/entry-client-2ac6917b.css"
    },
    {
      "type": "script",
      "href": "/assets/Card-9aaf02af.js"
    },
    {
      "type": "style",
      "href": "/assets/Card-73b0cb51.css"
    }
  ],
  "/teaching": [
    {
      "type": "script",
      "href": "/assets/teaching-cd6dcbdd.js"
    },
    {
      "type": "script",
      "href": "/assets/entry-client-503078e3.js"
    },
    {
      "type": "style",
      "href": "/assets/entry-client-2ac6917b.css"
    },
    {
      "type": "script",
      "href": "/assets/Card-9aaf02af.js"
    },
    {
      "type": "style",
      "href": "/assets/Card-73b0cb51.css"
    }
  ],
  "entry-client": [
    {
      "type": "script",
      "href": "/assets/entry-client-503078e3.js"
    },
    {
      "type": "style",
      "href": "/assets/entry-client-2ac6917b.css"
    }
  ],
  "index.html": []
}